outlines/__init__.py
outlines/_version.py
outlines/applications.py
outlines/caching.py
outlines/generator.py
outlines/grammars.py
outlines/inputs.py
outlines/py.typed
outlines/release_note.md
outlines/templates.py
outlines/backends/__init__.py
outlines/backends/base.py
outlines/backends/llguidance.py
outlines/backends/outlines_core.py
outlines/backends/xgrammar.py
outlines/grammars/arithmetic.lark
outlines/grammars/common.lark
outlines/grammars/json.lark
outlines/models/__init__.py
outlines/models/anthropic.py
outlines/models/base.py
outlines/models/dottxt.py
outlines/models/gemini.py
outlines/models/llamacpp.py
outlines/models/mistral.py
outlines/models/mlxlm.py
outlines/models/ollama.py
outlines/models/openai.py
outlines/models/sglang.py
outlines/models/tgi.py
outlines/models/tokenizer.py
outlines/models/transformers.py
outlines/models/utils.py
outlines/models/vllm.py
outlines/models/vllm_offline.py
outlines/processors/__init__.py
outlines/processors/base_logits_processor.py
outlines/processors/tensor_adapters/__init__.py
outlines/processors/tensor_adapters/base.py
outlines/processors/tensor_adapters/mlx.py
outlines/processors/tensor_adapters/numpy.py
outlines/processors/tensor_adapters/torch.py
outlines/types/__init__.py
outlines/types/airports.py
outlines/types/countries.py
outlines/types/dsl.py
outlines/types/json_schema_utils.py
outlines/types/utils.py
outlines/types/locale/__init__.py
outlines/types/locale/us.py
outlines-1.2.7.dist-info/licenses/LICENSE
outlines-1.2.7.dist-info/METADATA
outlines-1.2.7.dist-info/WHEEL
outlines-1.2.7.dist-info/top_level.txt
outlines-1.2.7.dist-info/RECORD
