Metadata-Version: 2.4
Name: outlines
Version: 1.2.7
Summary: Probabilistic Generative Model Programming
Author: Outlines Developers
License: Apache-2.0
Project-URL: homepage, https://github.com/dottxt-ai/outlines
Project-URL: documentation, https://dottxt-ai.github.io/outlines/
Project-URL: repository, https://github.com/dottxt-ai/outlines
Keywords: machine learning,deep learning,language models,structured generation
Classifier: Development Status :: 5 - Production/Stable
Classifier: Intended Audience :: Developers
Classifier: Intended Audience :: Information Technology
Classifier: Intended Audience :: Science/Research
Classifier: Operating System :: OS Independent
Classifier: Programming Language :: Python :: 3
Classifier: Topic :: Scientific/Engineering :: Artificial Intelligence
Requires-Python: <3.13,>=3.9
License-File: LICENSE
Requires-Dist: jinja2
Requires-Dist: cloudpickle
Requires-Dist: diskcache
Requires-Dist: pydantic>=2.0
Requires-Dist: jsonschema
Requires-Dist: pillow
Requires-Dist: typing_extensions
Requires-Dist: outlines_core==0.2.11
Requires-Dist: genson
Requires-Dist: jsonpath_ng
Provides-Extra: anthropic
Requires-Dist: anthropic; extra == "anthropic"
Provides-Extra: dottxt
Requires-Dist: dottxt; extra == "dottxt"
Provides-Extra: gemini
Requires-Dist: google-genai; extra == "gemini"
Provides-Extra: llamacpp
Requires-Dist: huggingface-hub; extra == "llamacpp"
Requires-Dist: llama-cpp-python; extra == "llamacpp"
Requires-Dist: numba; extra == "llamacpp"
Provides-Extra: mlxlm
Requires-Dist: datasets; extra == "mlxlm"
Requires-Dist: mlx; extra == "mlxlm"
Requires-Dist: mlx-lm; extra == "mlxlm"
Provides-Extra: ollama
Requires-Dist: ollama; extra == "ollama"
Provides-Extra: openai
Requires-Dist: openai; extra == "openai"
Provides-Extra: mistral
Requires-Dist: mistralai; extra == "mistral"
Provides-Extra: sglang
Requires-Dist: openai; extra == "sglang"
Provides-Extra: tgi
Requires-Dist: huggingface_hub; extra == "tgi"
Provides-Extra: transformers
Requires-Dist: accelerate; extra == "transformers"
Requires-Dist: datasets; extra == "transformers"
Requires-Dist: transformers; extra == "transformers"
Requires-Dist: setuptools; extra == "transformers"
Provides-Extra: vllm
Requires-Dist: openai; extra == "vllm"
Provides-Extra: xgrammar
Requires-Dist: xgrammar; extra == "xgrammar"
Provides-Extra: llguidance
Requires-Dist: llguidance; extra == "llguidance"
Provides-Extra: airports
Requires-Dist: airportsdata; extra == "airports"
Provides-Extra: countries
Requires-Dist: iso3166; extra == "countries"
Provides-Extra: test
Requires-Dist: pre-commit; extra == "test"
Requires-Dist: pytest; extra == "test"
Requires-Dist: pytest-benchmark; extra == "test"
Requires-Dist: pytest-cov; extra == "test"
Requires-Dist: pytest-mock; extra == "test"
Requires-Dist: pytest-asyncio; extra == "test"
Requires-Dist: coverage[toml]>=5.1; extra == "test"
Requires-Dist: diff-cover; extra == "test"
Requires-Dist: accelerate; extra == "test"
Requires-Dist: beartype<0.16.0; extra == "test"
Requires-Dist: responses; extra == "test"
Requires-Dist: llama-cpp-python; extra == "test"
Requires-Dist: mlx-lm>=0.19.2; (platform_machine == "arm64" and sys_platform == "darwin") and extra == "test"
Requires-Dist: huggingface_hub; extra == "test"
Requires-Dist: openai>=1.0.0; extra == "test"
Requires-Dist: datasets; extra == "test"
Requires-Dist: anthropic; extra == "test"
Requires-Dist: google-genai; extra == "test"
Requires-Dist: mistralai; extra == "test"
Requires-Dist: transformers; extra == "test"
Requires-Dist: pillow; extra == "test"
Requires-Dist: jax; extra == "test"
Requires-Dist: flax; extra == "test"
Requires-Dist: numpy<2.2.0,>=2.0.0; extra == "test"
Requires-Dist: numba; extra == "test"
Requires-Dist: torch>2.3.0; extra == "test"
Requires-Dist: tensorflow; extra == "test"
Requires-Dist: tf-keras; extra == "test"
Requires-Dist: ollama; extra == "test"
Requires-Dist: dottxt; extra == "test"
Requires-Dist: sentencepiece; extra == "test"
Requires-Dist: mkdocs_gen_files; extra == "test"
Requires-Dist: llguidance; extra == "test"
Requires-Dist: xgrammar; extra == "test"
Requires-Dist: airportsdata; extra == "test"
Requires-Dist: iso3166; extra == "test"
Requires-Dist: requests; extra == "test"
Provides-Extra: test-gpu
Requires-Dist: outlines[test]; extra == "test-gpu"
Requires-Dist: vllm; sys_platform == "linux" and extra == "test-gpu"
Dynamic: license-file
